{
  "annotations": [
    {
      "id": "2/21/2026, 5:35:11 PM",
      "taskId": "69999f076dfc3cd551e3a7e8",
      "page": "5",
      "answerPdfImageId": "69999f116dfc3cd551e3a80e",
      "answerPdfId": "69999f1b6dfc3cd551e3a839",
      "userId": "699970e5eb44a7329a04f58f",
      "iconUrl": "/check.png",
      "question": 1,
      "timeStamps": "2/21/2026, 5:35:11 PM",
      "x": 254.625,
      "y": 358.421875,
      "width": 150,
      "height": 80,
      "synced": false,
      "mark": 2,
      "parentQuestionId": null
    }
  ],
  "comments": []
}